dallCrawler/__init__.py
dallCrawler/crawler.py
dallCrawler-0.0.9.dist-info/LICENSE
dallCrawler-0.0.9.dist-info/METADATA
dallCrawler-0.0.9.dist-info/WHEEL
dallCrawler-0.0.9.dist-info/top_level.txt
dallCrawler-0.0.9.dist-info/RECORD
